pyJSL/RSAhandler.py
pyJSL/__init__.py
pyJSL-0.1.1.dist-info/LICENSE
pyJSL-0.1.1.dist-info/METADATA
pyJSL-0.1.1.dist-info/WHEEL
pyJSL-0.1.1.dist-info/top_level.txt
pyJSL-0.1.1.dist-info/RECORD
